odoo/addons/helpdesk_mgmt_template/README.rst
odoo/addons/helpdesk_mgmt_template/__init__.py
odoo/addons/helpdesk_mgmt_template/__manifest__.py
odoo/addons/helpdesk_mgmt_template/i18n/helpdesk_mgmt_template.pot
odoo/addons/helpdesk_mgmt_template/i18n/it.po
odoo/addons/helpdesk_mgmt_template/i18n/pt_BR.po
odoo/addons/helpdesk_mgmt_template/models/__init__.py
odoo/addons/helpdesk_mgmt_template/models/helpdesk_ticket.py
odoo/addons/helpdesk_mgmt_template/models/helpdesk_ticket_category.py
odoo/addons/helpdesk_mgmt_template/readme/CONFIGURE.rst
odoo/addons/helpdesk_mgmt_template/readme/CONTRIBUTORS.rst
odoo/addons/helpdesk_mgmt_template/readme/DESCRIPTION.rst
odoo/addons/helpdesk_mgmt_template/readme/USAGE.rst
odoo/addons/helpdesk_mgmt_template/static/description/icon.png
odoo/addons/helpdesk_mgmt_template/static/description/index.html
odoo/addons/helpdesk_mgmt_template/tests/__init__.py
odoo/addons/helpdesk_mgmt_template/tests/test_helpdesk_ticket.py
odoo/addons/helpdesk_mgmt_template/views/helpdesk_ticket_category_views.xml
odoo/addons/helpdesk_mgmt_template/views/helpdesk_ticket_team_views.xml
odoo/addons/helpdesk_mgmt_template/views/helpdesk_ticket_views.xml
odoo_addon_helpdesk_mgmt_template-16.0.1.0.0.6.dist-info/METADATA
odoo_addon_helpdesk_mgmt_template-16.0.1.0.0.6.dist-info/WHEEL
odoo_addon_helpdesk_mgmt_template-16.0.1.0.0.6.dist-info/top_level.txt
odoo_addon_helpdesk_mgmt_template-16.0.1.0.0.6.dist-info/RECORD
